[{
    "title": "OTP",
    "url": "(ﾉಥ益ಥ）ﾉ﻿ ┻━┻",
    "body": "Henri Coandă International Airport"
  }, {
    "title": "GYE",
    "url": "(ﾉಥ益ಥ）ﾉ﻿ ┻━┻",
    "body": "José Joaquín de Olmedo International Airport"
  }, {
    "title": "JVL",
    "url": "(ﾉಥ益ಥ）ﾉ﻿ ┻━┻",
    "body": "Southern Wisconsin Regional Airport"
  }, {
    "title": "GTY",
    "url": "(ﾉಥ益ಥ）ﾉ﻿ ┻━┻",
    "body": "Gettysburg Regional Airport"
  }, {
    "title": "AUN",
    "url": "(ﾉಥ益ಥ）ﾉ﻿ ┻━┻",
    "body": "Auburn Municipal Airport"
  }]